tests/__init__.py
tests/test_function_process.py
tests/test_timeout.py
tests/test_timeout_exception.py
timeout/__init__.py
timeout/timeout_decorator.py
py_timeout-0.0.1.dist-info/LICENSE
py_timeout-0.0.1.dist-info/METADATA
py_timeout-0.0.1.dist-info/WHEEL
py_timeout-0.0.1.dist-info/top_level.txt
py_timeout-0.0.1.dist-info/RECORD
