Metadata-Version: 2.1
Name: py-timeout
Version: 0.0.1
Summary: Process based timeout context decorator
Home-page: https://github.com/YADRO-KNS/py-timeout
Author: Sergey Parshin
Author-email: s.parshin@yadro.com
License: UNKNOWN
Platform: UNKNOWN
Classifier: Development Status :: 3 - Alpha
Classifier: Programming Language :: Python :: 3.6
Classifier: Programming Language :: Python :: 3.7
Classifier: Programming Language :: Python :: 3.8
Classifier: Programming Language :: Python :: 3.9
Classifier: License :: OSI Approved :: MIT License
Classifier: Operating System :: OS Independent
